setup.py
akshey_dsnd_probability/Binomialdistribution.py
akshey_dsnd_probability/Gaussiandistribution.py
akshey_dsnd_probability/Generaldistribution.py
akshey_dsnd_probability/__init__.py
akshey_dsnd_probability.egg-info/PKG-INFO
akshey_dsnd_probability.egg-info/SOURCES.txt
akshey_dsnd_probability.egg-info/dependency_links.txt
akshey_dsnd_probability.egg-info/not-zip-safe
akshey_dsnd_probability.egg-info/top_level.txt