Metadata-Version: 1.0
Name: akshey-dsnd-probability
Version: 0.1
Summary: Gaussian distributions
Home-page: UNKNOWN
Author: Akshey Nama
Author-email: UNKNOWN
License: UNKNOWN
Platform: UNKNOWN
